{
  "name": "Riding Horse",
  "size": "Large",
  "type": "Beast",
  "alignment": "Unaligned",
  "armor_class": 11,
  "hit_points": {
    "average": 13,
    "dice": "2d10 + 2"
  },
  "speed": {
    "walk": { "value": 60, "unit": "ft." }
  },
  "initiative": {
    "modifier": 1,
    "score": 11
  },
  "ability_scores": {
    "strength": { "score": 16, "modifier": 3, "save": 3 },
    "dexterity": { "score": 13, "modifier": 1, "save": 1 },
    "constitution": { "score": 12, "modifier": 1, "save": 1 },
    "intelligence": { "score": 2, "modifier": -4, "save": -4 },
    "wisdom": { "score": 11, "modifier": 0, "save": 0 },
    "charisma": { "score": 7, "modifier": -2, "save": -2 }
  },
  "senses": {
    "passive_perception": 10
  },
  "languages": [],
  "challenge_rating": {
    "rating": "1/4",
    "xp": 50
  },
  "proficiency_bonus": 2,
  "actions": [
    {
      "name": "Hooves",
      "description": "Melee Attack Roll: +5, reach 5 ft. Hit: 7 (1d8 + 3) Bludgeoning damage."
    }
  ]
}