{
  "name": "Giant Seahorse",
  "size": "Large",
  "type": "Beast",
  "alignment": "Unaligned",
  "armor_class": 14,
  "hit_points": {
    "average": 16,
    "dice": "3d10"
  },
  "speed": {
    "walk": { "value": 5, "unit": "ft." },
    "swim": { "value": 40, "unit": "ft." }
  },
  "initiative": {
    "modifier": 1,
    "score": 11
  },
  "ability_scores": {
    "strength": { "score": 15, "modifier": 2, "save": 2 },
    "dexterity": { "score": 12, "modifier": 1, "save": 1 },
    "constitution": { "score": 11, "modifier": 0, "save": 0 },
    "intelligence": { "score": 2, "modifier": -4, "save": -4 },
    "wisdom": { "score": 12, "modifier": 1, "save": 1 },
    "charisma": { "score": 5, "modifier": -3, "save": -3 }
  },
  "skills": [
    { "name": "Perception", "modifier": 2 }
  ],
  "senses": {
    "passive_perception": 11
  },
  "languages": [],
  "challenge_rating": {
    "rating": "1/2",
    "xp": 100
  },
  "proficiency_bonus": 2,
  "traits": [
    {
      "name": "Water Breathing",
      "description": "The seahorse can breathe only underwater."
    }
  ],
  "actions": [
    {
      "name": "Ram",
      "description": "Melee Attack Roll: +4, reach 5 ft. Hit: 9 (2d6 + 2) Bludgeoning damage, or 11 (2d8 + 2) Bludgeoning damage if the seahorse moved 20+ feet straight toward the target immediately before the hit."
    }
  ],
  "bonus_actions": [
    {
      "name": "Bubble Dash",
      "description": "While underwater, the seahorse moves up to half its Swim Speed without provoking Opportunity Attacks."
    }
  ]
}